{
 "Week": "2025-01-08",
 "LastWeek": "",
 "X": 0.7852225317639057,
 "Programs": [
  {
   "Program": "cmd/asm",
   "Version": "go1.23.4",
   "GoVersion": "go1.23.4",
   "GOOS": "linux",
   "GOARCH": "arm64",
   "Counters": {
    "asm/flag:D": 79,
    "asm/flag:I": 79,
    "asm/flag:gensymabis": 30,
    "asm/flag:o": 79,
    "asm/flag:p": 79,
    "asm/flag:trimpath": 79,
    "asm/invocations": 79
   },
   "Stacks": {}
  },
  {
   "Program": "cmd/cgo",
   "Version": "go1.23.4",
   "GoVersion": "go1.23.4",
   "GOOS": "linux",
   "GOARCH": "arm64",
   "Counters": {
    "cgo/flag:dynimport": 3,
    "cgo/flag:dynlinker": 1,
    "cgo/flag:dynout": 3,
    "cgo/flag:dynpackage": 3,
    "cgo/flag:import_runtime_cgo": 1,
    "cgo/flag:import_syscall": 1,
    "cgo/flag:importpath": 3,
    "cgo/flag:ldflags": 3,
    "cgo/flag:objdir": 3,
    "cgo/invocations": 6
   },
   "Stacks": {}
  },
  {
   "Program": "cmd/compile",
   "Version": "go1.23.4",
   "GoVersion": "go1.23.4",
   "GOOS": "linux",
   "GOARCH": "arm64",
   "Counters": {
    "compile/flag:asmhdr": 30,
    "compile/flag:buildid": 418,
    "compile/flag:c": 418,
    "compile/flag:complete": 381,
    "compile/flag:embedcfg": 1,
    "compile/flag:goversion": 418,
    "compile/flag:importcfg": 418,
    "compile/flag:lang": 418,
    "compile/flag:nolocalimports": 418,
    "compile/flag:o": 418,
    "compile/flag:p": 418,
    "compile/flag:pack": 418,
    "compile/flag:std": 169,
    "compile/flag:symabis": 30,
    "compile/flag:trimpath": 418,
    "compile/invocations": 438
   },
   "Stacks": {}
  },
  {
   "Program": "cmd/go",
   "Version": "go1.23.4",
   "GoVersion": "go1.23.4",
   "GOOS": "linux",
   "GOARCH": "arm64",
   "Counters": {
    "go/buildcache/hit": 160,
    "go/buildcache/miss": 420,
    "go/buildcache/stdlib-recompiled": 2,
    "go/goroot:usr-lib-golang": 2,
    "go/invocations": 2,
    "go/mode:module": 2,
    "go/platform/host/linux/major-version:6": 2,
    "go/platform/host/linux/version:6-12": 2,
    "go/platform/target/goarch:arm64": 2,
    "go/platform/target/goarm64:v8.0": 2,
    "go/platform/target/goos:linux": 2,
    "go/subcommand:build": 2
   },
   "Stacks": {}
  },
  {
   "Program": "cmd/link",
   "Version": "go1.23.4",
   "GoVersion": "go1.23.4",
   "GOOS": "linux",
   "GOARCH": "arm64",
   "Counters": {
    "link/flag:X": 1,
    "link/flag:buildid": 2,
    "link/flag:buildmode": 2,
    "link/flag:extld": 2,
    "link/flag:importcfg": 2,
    "link/flag:o": 2,
    "link/invocations": 4
   },
   "Stacks": {}
  }
 ],
 "Config": "v0.0.0-0"
}